anova_utils/__init__.py
anova_utils/anova_utils_functions.py
anova_utils-0.3.3.dist-info/LICENSE
anova_utils-0.3.3.dist-info/WHEEL
anova_utils-0.3.3.dist-info/METADATA
anova_utils-0.3.3.dist-info/RECORD
